pimgu/__init__.py
pimgu/applet.py
pimgu-5.4.2023.7.dist-info/LICENSE
pimgu-5.4.2023.7.dist-info/METADATA
pimgu-5.4.2023.7.dist-info/WHEEL
pimgu-5.4.2023.7.dist-info/top_level.txt
pimgu-5.4.2023.7.dist-info/RECORD
