Metadata-Version: 2.1
Name: pimgu
Version: 5.4.2023.7
Summary: A simple framework for creating robust 2D GUI applications using Pygame and ImGui.
Home-page: https://github.com/iwilkey/pimgu
Author: Ian Wilkey
Author-email: iwilkey@mail.bradley.edu
Classifier: Development Status :: 3 - Alpha
Classifier: License :: OSI Approved :: MIT License
Classifier: Programming Language :: Python :: 3
Classifier: Programming Language :: Python :: 3.6
Classifier: Programming Language :: Python :: 3.7
Classifier: Programming Language :: Python :: 3.8
Classifier: Programming Language :: Python :: 3.9
Classifier: Programming Language :: Python :: 3.10
Classifier: Programming Language :: Python :: 3.11
License-File: LICENSE
Requires-Dist: pygame
Requires-Dist: PyOpenGL
Requires-Dist: imgui
Requires-Dist: numpy
